ZixueShiMenShouyiFix1/README.md
ZixueShiMenShouyiFix1/__init__.py
ZixueShiMenShouyiFix1/__main__.py
ZixueShiMenShouyiFix1/file.epub
ZixueShiMenShouyiFix1/index.html
ZixueShiMenShouyiFix1/css/__init__.py
ZixueShiMenShouyiFix1/css/annotations.css
ZixueShiMenShouyiFix1/css/main.css
ZixueShiMenShouyiFix1/css/normalize.css
ZixueShiMenShouyiFix1/css/popup.css
ZixueShiMenShouyiFix1/font/__init__.py
ZixueShiMenShouyiFix1/font/fontello.eot
ZixueShiMenShouyiFix1/font/fontello.svg
ZixueShiMenShouyiFix1/font/fontello.ttf
ZixueShiMenShouyiFix1/font/fontello.woff
ZixueShiMenShouyiFix1/img/__init__.py
ZixueShiMenShouyiFix1/img/annotator-glyph-sprite.png
ZixueShiMenShouyiFix1/img/annotator-icon-sprite.png
ZixueShiMenShouyiFix1/img/apple-touch-icon.png
ZixueShiMenShouyiFix1/img/cancelfullscreen.png
ZixueShiMenShouyiFix1/img/close.png
ZixueShiMenShouyiFix1/img/fullscreen.png
ZixueShiMenShouyiFix1/img/loader.gif
ZixueShiMenShouyiFix1/img/menu-icon.png
ZixueShiMenShouyiFix1/img/save.png
ZixueShiMenShouyiFix1/img/saved.png
ZixueShiMenShouyiFix1/img/settings-s.png
ZixueShiMenShouyiFix1/img/settings.png
ZixueShiMenShouyiFix1/img/star.png
ZixueShiMenShouyiFix1/js/__init__.py
ZixueShiMenShouyiFix1/js/epub.js
ZixueShiMenShouyiFix1/js/epub.min.js
ZixueShiMenShouyiFix1/js/epub.min.map
ZixueShiMenShouyiFix1/js/hooks.min.js
ZixueShiMenShouyiFix1/js/hooks.min.map
ZixueShiMenShouyiFix1/js/reader.js
ZixueShiMenShouyiFix1/js/reader.js.map
ZixueShiMenShouyiFix1/js/reader.min.js
ZixueShiMenShouyiFix1/js/reader.min.map
ZixueShiMenShouyiFix1/js/hooks/__init__.py
ZixueShiMenShouyiFix1/js/hooks/extensions/__init__.py
ZixueShiMenShouyiFix1/js/hooks/extensions/highlight.js
ZixueShiMenShouyiFix1/js/libs/__init__.py
ZixueShiMenShouyiFix1/js/libs/jquery.min.js
ZixueShiMenShouyiFix1/js/libs/localforage.min.js
ZixueShiMenShouyiFix1/js/libs/screenfull.js
ZixueShiMenShouyiFix1/js/libs/screenfull.min.js
ZixueShiMenShouyiFix1/js/libs/zip.min.js
ZixueShiMenShouyiFix1/js/plugins/__init__.py
zixue_shi_men_shouyi_fix1-2025.3.24.2.dist-info/METADATA
zixue_shi_men_shouyi_fix1-2025.3.24.2.dist-info/WHEEL
zixue_shi_men_shouyi_fix1-2025.3.24.2.dist-info/entry_points.txt
zixue_shi_men_shouyi_fix1-2025.3.24.2.dist-info/top_level.txt
zixue_shi_men_shouyi_fix1-2025.3.24.2.dist-info/RECORD
